[{"id":"c7491e02.e1fe5","type":"tab","label":"Manual Switch","disabled":false,"info":""},{"id":"f929015.59ef5","type":"mqtt in","z":"c7491e02.e1fe5","name":"","topic":"cmd/relaybox/switch1","qos":"2","datatype":"auto","broker":"ddd76ee4.a8006","x":160,"y":1760,"wires":[["bbdc6d1c.2beb6"]]},{"id":"bbdc6d1c.2beb6","type":"debug","z":"c7491e02.e1fe5","name":"arduino_debug","active":false,"tosidebar":true,"console":false,"tostatus":false,"complete":"payload","targetType":"msg","x":400,"y":1760,"wires":[]},{"id":"cb79b2d.236005","type":"inject","z":"c7491e02.e1fe5","name":"","topic":"","payload":"false","payloadType":"bool","repeat":"","crontab":"","once":false,"onceDelay":0.1,"x":130,"y":1900,"wires":[["1c64c4d3.139cbb"]]},{"id":"1c64c4d3.139cbb","type":"mqtt out","z":"c7491e02.e1fe5","name":"","topic":"status/relaybox/switch1","qos":"","retain":"","broker":"ddd76ee4.a8006","x":370,"y":1860,"wires":[]},{"id":"60e98d59.69fd64","type":"inject","z":"c7491e02.e1fe5","name":"","topic":"","payload":"true","payloadType":"bool","repeat":"","crontab":"","once":false,"onceDelay":0.1,"x":130,"y":1840,"wires":[["1c64c4d3.139cbb"]]},{"id":"c7918c02.2004e","type":"comment","z":"c7491e02.e1fe5","name":"simulate Arduino","info":"","x":140,"y":1700,"wires":[]},{"id":"6dcf3cb6.cdc104","type":"ui_switch","z":"c7491e02.e1fe5","name":"","label":"4_powerhead","tooltip":"","group":"a63e60d8.5af38","order":4,"width":"0","height":"0","passthru":true,"decouple":"false","topic":"","style":"","onvalue":"1","onvalueType":"num","onicon":"","oncolor":"","offvalue":"0","offvalueType":"num","officon":"","offcolor":"","x":360,"y":500,"wires":[["db0567cf.34af18"]]},{"id":"b074bcc.bdcce4","type":"mqtt out","z":"c7491e02.e1fe5","name":"","topic":"cmd/relaybox/switch4","qos":"","retain":"","broker":"ddd76ee4.a8006","x":800,"y":500,"wires":[]},{"id":"3785e810.2858b8","type":"mqtt in","z":"c7491e02.e1fe5","name":"","topic":"status/relaybox/switch4","qos":"2","datatype":"json","broker":"ddd76ee4.a8006","x":140,"y":480,"wires":[["6dcf3cb6.cdc104","45598beb.836524"]]},{"id":"db0567cf.34af18","type":"function","z":"c7491e02.e1fe5","name":"switch4","func":"var name=node.name;\n\nvar old_switch=global.get(name)||0;\nvar new_switch=msg.payload;\nif (old_switch!=new_switch){\n    global.set(name,new_switch);\n    return msg;    \n}\n\n","outputs":1,"noerr":0,"x":620,"y":500,"wires":[["b074bcc.bdcce4"]]},{"id":"2b5c3386.63246c","type":"ui_switch","z":"c7491e02.e1fe5","name":"","label":"5_return_pump","tooltip":"","group":"a63e60d8.5af38","order":5,"width":"0","height":"0","passthru":true,"decouple":"false","topic":"","style":"","onvalue":"1","onvalueType":"num","onicon":"","oncolor":"","offvalue":"0","offvalueType":"num","officon":"","offcolor":"","x":360,"y":660,"wires":[["962692f7.9c064"]]},{"id":"9ab35b26.bb16b8","type":"mqtt out","z":"c7491e02.e1fe5","name":"","topic":"cmd/relaybox/switch5","qos":"","retain":"","broker":"ddd76ee4.a8006","x":800,"y":660,"wires":[]},{"id":"770ca97c.64f6a8","type":"mqtt in","z":"c7491e02.e1fe5","name":"","topic":"status/relaybox/switch5","qos":"2","datatype":"json","broker":"ddd76ee4.a8006","x":140,"y":640,"wires":[["2b5c3386.63246c","1212fa15.a5b566"]]},{"id":"962692f7.9c064","type":"function","z":"c7491e02.e1fe5","name":"switch5","func":"var name=node.name;\n\nvar old_switch=global.get(name)||0;\nvar new_switch=msg.payload;\nif (old_switch!=new_switch){\n    global.set(name,new_switch);\n    return msg;    \n}\n\n","outputs":1,"noerr":0,"x":620,"y":660,"wires":[["9ab35b26.bb16b8"]]},{"id":"da3477ef.8a6d88","type":"ui_switch","z":"c7491e02.e1fe5","name":"","label":"6_skimmer","tooltip":"","group":"a63e60d8.5af38","order":6,"width":"0","height":"0","passthru":true,"decouple":"false","topic":"","style":"","onvalue":"1","onvalueType":"num","onicon":"","oncolor":"","offvalue":"0","offvalueType":"num","officon":"","offcolor":"","x":350,"y":840,"wires":[["2a03a589.8bb95a"]]},{"id":"bb352b29.b94dd8","type":"mqtt out","z":"c7491e02.e1fe5","name":"","topic":"cmd/relaybox/switch6","qos":"","retain":"","broker":"ddd76ee4.a8006","x":800,"y":840,"wires":[]},{"id":"556c271b.7ac6b8","type":"mqtt in","z":"c7491e02.e1fe5","name":"","topic":"status/relaybox/switch6","qos":"2","datatype":"json","broker":"ddd76ee4.a8006","x":140,"y":820,"wires":[["da3477ef.8a6d88","ebcd0549.b2b538"]]},{"id":"2a03a589.8bb95a","type":"function","z":"c7491e02.e1fe5","name":"switch6","func":"var name=node.name;\n\nvar old_switch=global.get(name)||0;\nvar new_switch=msg.payload;\nif (old_switch!=new_switch){\n    global.set(name,new_switch);\n    return msg;    \n}\n\n","outputs":1,"noerr":0,"x":620,"y":840,"wires":[["bb352b29.b94dd8"]]},{"id":"acee05a7.568308","type":"ui_switch","z":"c7491e02.e1fe5","name":"","label":"7_chiller","tooltip":"","group":"a63e60d8.5af38","order":7,"width":"0","height":"0","passthru":true,"decouple":"false","topic":"","style":"","onvalue":"1","onvalueType":"num","onicon":"","oncolor":"","offvalue":"0","offvalueType":"num","officon":"","offcolor":"","x":340,"y":1000,"wires":[["6628db85.0a6364"]]},{"id":"4e869a8a.aeaee4","type":"mqtt out","z":"c7491e02.e1fe5","name":"","topic":"cmd/relaybox/switch7","qos":"","retain":"","broker":"ddd76ee4.a8006","x":800,"y":1000,"wires":[]},{"id":"ea96551b.23e628","type":"mqtt in","z":"c7491e02.e1fe5","name":"","topic":"status/relaybox/switch7","qos":"2","datatype":"json","broker":"ddd76ee4.a8006","x":140,"y":980,"wires":[["acee05a7.568308","3d3dca6d.819f66"]]},{"id":"6628db85.0a6364","type":"function","z":"c7491e02.e1fe5","name":"switch7","func":"var name=node.name;\n\nvar old_switch=global.get(name)||0;\nvar new_switch=msg.payload;\nif (old_switch!=new_switch){\n    global.set(name,new_switch);\n    return msg;    \n}\n\n","outputs":1,"noerr":0,"x":620,"y":1000,"wires":[["4e869a8a.aeaee4"]]},{"id":"f54cab92.5d9a88","type":"ui_switch","z":"c7491e02.e1fe5","name":"","label":"8_refugium_powerhead","tooltip":"","group":"a63e60d8.5af38","order":8,"width":"0","height":"0","passthru":true,"decouple":"false","topic":"","style":"","onvalue":"1","onvalueType":"num","onicon":"","oncolor":"","offvalue":"0","offvalueType":"num","officon":"","offcolor":"","x":390,"y":1180,"wires":[["51454b5c.fe3274"]]},{"id":"4288c7aa.0a5348","type":"mqtt out","z":"c7491e02.e1fe5","name":"","topic":"cmd/relaybox/switch8","qos":"","retain":"","broker":"ddd76ee4.a8006","x":800,"y":1180,"wires":[]},{"id":"bdea488d.f7fa38","type":"mqtt in","z":"c7491e02.e1fe5","name":"","topic":"status/relaybox/switch8","qos":"2","datatype":"json","broker":"ddd76ee4.a8006","x":140,"y":1160,"wires":[["f54cab92.5d9a88","ac532550.cf7358"]]},{"id":"51454b5c.fe3274","type":"function","z":"c7491e02.e1fe5","name":"switch8","func":"var name=node.name;\n\nvar old_switch=global.get(name)||0;\nvar new_switch=msg.payload;\nif (old_switch!=new_switch){\n    global.set(name,new_switch);\n    return msg;    \n}\n\n","outputs":1,"noerr":0,"x":620,"y":1180,"wires":[["4288c7aa.0a5348"]]},{"id":"45598beb.836524","type":"influxdb out","z":"c7491e02.e1fe5","influxdb":"a84d487c.0c7558","name":"","measurement":"RelayStatus4","precision":"","retentionPolicy":"","x":420,"y":460,"wires":[]},{"id":"1212fa15.a5b566","type":"influxdb out","z":"c7491e02.e1fe5","influxdb":"a84d487c.0c7558","name":"","measurement":"RelayStatus5","precision":"","retentionPolicy":"","x":420,"y":620,"wires":[]},{"id":"ebcd0549.b2b538","type":"influxdb out","z":"c7491e02.e1fe5","influxdb":"a84d487c.0c7558","name":"","measurement":"RelayStatus6","precision":"","retentionPolicy":"","x":420,"y":800,"wires":[]},{"id":"3d3dca6d.819f66","type":"influxdb out","z":"c7491e02.e1fe5","influxdb":"a84d487c.0c7558","name":"","measurement":"RelayStatus7","precision":"","retentionPolicy":"","x":420,"y":960,"wires":[]},{"id":"ac532550.cf7358","type":"influxdb out","z":"c7491e02.e1fe5","influxdb":"a84d487c.0c7558","name":"","measurement":"RelayStatus8","precision":"","retentionPolicy":"","x":420,"y":1140,"wires":[]},{"id":"a2e1e270.63e75","type":"mqtt in","z":"c7491e02.e1fe5","name":"","topic":"status/relaybox/switch1","qos":"2","datatype":"json","broker":"ddd76ee4.a8006","x":140,"y":80,"wires":[["7cc1f52b.77ddfc","2975987e.4c3368"]]},{"id":"7cc1f52b.77ddfc","type":"influxdb out","z":"c7491e02.e1fe5","influxdb":"a84d487c.0c7558","name":"","measurement":"RelayStatus1","precision":"","retentionPolicy":"","x":420,"y":60,"wires":[]},{"id":"19b29f26.4aec81","type":"mqtt in","z":"c7491e02.e1fe5","name":"","topic":"status/relaybox/switch2","qos":"2","datatype":"json","broker":"ddd76ee4.a8006","x":140,"y":180,"wires":[["b7abd52c.3e9618","a44e60cd.d40ed"]]},{"id":"b7abd52c.3e9618","type":"influxdb out","z":"c7491e02.e1fe5","influxdb":"a84d487c.0c7558","name":"","measurement":"RelayStatus2","precision":"","retentionPolicy":"","x":420,"y":160,"wires":[]},{"id":"52e7daf2.3aa444","type":"mqtt in","z":"c7491e02.e1fe5","name":"","topic":"status/relaybox/switch3","qos":"2","datatype":"json","broker":"ddd76ee4.a8006","x":140,"y":320,"wires":[["b3cf3270.1b24d","c85d5c97.f55f6"]]},{"id":"b3cf3270.1b24d","type":"influxdb out","z":"c7491e02.e1fe5","influxdb":"a84d487c.0c7558","name":"","measurement":"RelayStatus3","precision":"","retentionPolicy":"","x":420,"y":300,"wires":[]},{"id":"2975987e.4c3368","type":"ui_led","z":"c7491e02.e1fe5","group":"a63e60d8.5af38","order":1,"width":0,"height":0,"label":"1_main_light","labelPlacement":"left","labelAlignment":"left","colorForValue":[{"color":"red","value":"0","valueType":"num"},{"color":"green","value":"1","valueType":"num"}],"allowColorForValueInMessage":false,"name":"","x":330,"y":100,"wires":[]},{"id":"a44e60cd.d40ed","type":"ui_led","z":"c7491e02.e1fe5","group":"a63e60d8.5af38","order":2,"width":0,"height":0,"label":"2_refugium_light","labelPlacement":"left","labelAlignment":"left","colorForValue":[{"color":"red","value":"0","valueType":"num"},{"color":"green","value":"1","valueType":"num"}],"allowColorForValueInMessage":false,"name":"","x":330,"y":200,"wires":[]},{"id":"c85d5c97.f55f6","type":"ui_led","z":"c7491e02.e1fe5","group":"a63e60d8.5af38","order":3,"width":0,"height":0,"label":"3_fan","labelPlacement":"left","labelAlignment":"left","colorForValue":[{"color":"red","value":"0","valueType":"num"},{"color":"green","value":"1","valueType":"num"}],"allowColorForValueInMessage":false,"name":"","x":330,"y":340,"wires":[]},{"id":"896edfe5.7587c","type":"mqtt in","z":"c7491e02.e1fe5","name":"","topic":"status/relaybox_empty/switch9","qos":"2","datatype":"json","broker":"ddd76ee4.a8006","x":210,"y":2140,"wires":[["79068d98.01a1c4","b1fc65de.5f18b8"]]},{"id":"79068d98.01a1c4","type":"influxdb out","z":"c7491e02.e1fe5","influxdb":"a84d487c.0c7558","name":"","measurement":"RelayStatus9","precision":"","retentionPolicy":"","x":540,"y":2140,"wires":[]},{"id":"b1fc65de.5f18b8","type":"debug","z":"c7491e02.e1fe5","name":"","active":true,"tosidebar":true,"console":false,"tostatus":false,"complete":"false","x":470,"y":2200,"wires":[]},{"id":"4465dbfe.c2e834","type":"comment","z":"c7491e02.e1fe5","name":"For test with esp32_empty","info":"","x":190,"y":2080,"wires":[]},{"id":"ddd76ee4.a8006","type":"mqtt-broker","z":"","name":"","broker":"mqtt","port":"1883","clientid":"","usetls":false,"compatmode":true,"keepalive":"60","cleansession":true,"birthTopic":"","birthQos":"0","birthPayload":"","closeTopic":"","closeQos":"0","closePayload":"","willTopic":"","willQos":"0","willPayload":""},{"id":"a63e60d8.5af38","type":"ui_group","z":"","name":"Switchs","tab":"74d84887.fd0e28","disp":true,"width":"6","collapse":false},{"id":"a84d487c.0c7558","type":"influxdb","z":"","hostname":"influxdb","port":"8086","protocol":"http","database":"mytank","name":"","usetls":false,"tls":""},{"id":"74d84887.fd0e28","type":"ui_tab","z":"","name":"Power","icon":"dashboard","order":8,"disabled":false,"hidden":false}]